pdfCatalog.py
pdfCatalog-1.0.2.dist-info/DESCRIPTION.rst
pdfCatalog-1.0.2.dist-info/METADATA
pdfCatalog-1.0.2.dist-info/RECORD
pdfCatalog-1.0.2.dist-info/WHEEL
pdfCatalog-1.0.2.dist-info/entry_points.txt
pdfCatalog-1.0.2.dist-info/metadata.json
pdfCatalog-1.0.2.dist-info/top_level.txt
