Metadata-Version: 2.0
Name: pdfCatalog
Version: 1.0.2
Summary: Build catalogs for PDF documents automatically.
Home-page: https://github.com/zyingzhou/pdfCatalog
Author: zhiying zhou
Author-email: zhiyingstatham@qq.com
License: GNU Affero General Public License v3.0
Platform: UNKNOWN
Classifier: Environment :: Console
Classifier: Operating System :: OS Independent
Classifier: Programming Language :: Python
Classifier: Programming Language :: Python :: 3
Classifier: Programming Language :: Python :: 3.5
Classifier: Programming Language :: Python :: 3.6
Classifier: Programming Language :: Python :: 3.7
Classifier: Programming Language :: Python :: 3.8
Classifier: Topic :: Software Development :: Libraries :: Python Modules
Requires-Dist: pymupdf
